{"title": "Un polo agr\u00edcola con m\u00e1s reservas que aportes", "body": "\n\nNo puede ser que aqu\u00ed en Troya, del municipio de Manzanillo, donde se\nencuentran tres formas productivas (dos ccs y una unidad de la granja urbana)\ntenga que venir la empresa de acopio municipal, con producciones a m\u00e1s de 20\nkil\u00f3metros, cuando existe un alto potencial productivo para abastecer al\nconsejo, principalmente de viandas, hortalizas, granos y frutas, y aportar\ngrandes vol\u00famenes al municipio.\n\nSe habla mucho del polo productivo de Troya, atendido por un trabajador de la\ngranja urbana, con cierta atenci\u00f3n, pero son muchas m\u00e1s las \u00e1reas vac\u00edas, e\nincluso las que bulducearon el a\u00f1o pasado, se volvieron a perder en marab\u00fa.\nCreo que un verdadero polo productivo debe incluir a todos los campesinos\nalrededor, pero con nosotros nadie se ha reunido para conformar un plan de\nacci\u00f3n.\n\nEsta zona cuenta con suelos ideales para la producci\u00f3n agropecuaria y con una\npeque\u00f1a inversi\u00f3n en la electrificaci\u00f3n. Se pueden lograr altos potenciales\nproductivos con m\u00ednimos recursos. Hablamos de unas diez caballer\u00edas de tierra.\nLos pocos recursos asignados a nuestra ccs nunca llegan en tiempo, las botas\nque a veces venden no tienen ninguna calidad, con acopio vale la balanza que\nellos usan, no hacen muestreos del producto, deciden arbitrariamente la\ncalidad, y cuando les vendemos perdemos los sacos.\n\nLa unidad de Gelma hoy pr\u00e1cticamente no cumple el objetivo para el que fue\ncreada. Por ejemplo, la cosecha de ma\u00edz est\u00e1 en la recta final y no se ha\nvendido un solo saco, y tienen en existencias, seg\u00fan el presidente de nuestra\nccs, pero no han hecho la asignaci\u00f3n que corresponde a las unidades\nproductoras.\n\nNada de esto ayuda a que el autoabastecimiento sea una realidad en el\nmunicipio de Manzanillo.\n\nJos\u00e9 Orlando Figueredo Villaverde,\n\nMart\u00ed, No. 49, Troya, Manzanillo, Granma.\n\n", "link": "https://www.granma.cu/cartas/2020-10-16/un-polo-agricola-con-mas-reservas-que-aportes", "original_letter_link": null, "is_response": false, "date": "2020-10-16", "comments": []}