{"title": "Sin respuesta y sin soluci\u00f3n", "body": "\n\nLa direcci\u00f3n municipal de Planificaci\u00f3n F\u00edsica en Urbano Noris le adjudic\u00f3 una\nporci\u00f3n de terreno a un vecino sin verificar que era parte de mi propiedad. A\npesar de dirigirme a esa entidad y plantear mi inconformidad al respecto, hace\nya tres meses, no se ha subsanado ese error y no tengo respuesta ni del\nmunicipio ni de la provincia, instancia a la cual tambi\u00e9n se le notific\u00f3 lo\nocurrido. Necesito conocer el mecanismo o la v\u00eda para la soluci\u00f3n de este\nproblema.\n\nJorge Luis Cuba Espinosa,\n\nCalle 28 No. 1909, e/ 19 y 23,\n\nUrbano Noris, Holgu\u00edn.\n\n", "link": "https://www.granma.cu/cartas/2020-01-25/sin-respuesta-y-sin-solucion", "original_letter_link": null, "is_response": false, "date": "2020-01-25", "comments": []}