{"title": "Exige su comprobante de pago", "body": "\n\nEn la tarde noche del d\u00eda 4 de enero de 2021, aproximadamente a las 6:30 p.m.,\ncobr\u00e9 el cheque de ayuda monetaria que me entreg\u00f3 Asistencia Social. Fui\natendido en la caja de ahorro No. 5 de la sucursal a la que tributa el \u00d3rgano\nde Trabajo a Bandec, que radica en la Plaza de los Trabajadores. Al terminar\nla transacci\u00f3n monetaria, le pregunt\u00e9 a la joven bancaria que por qu\u00e9 no me\nentreg\u00f3 el comprobante del pago que recibo. Me respondi\u00f3, decentemente, pero\ncon firmeza, que no pod\u00eda dar comprobante a los clientes. \u00bfDesde cu\u00e1ndo sucede\nesto?, le dije, y me  \ncontest\u00f3 que desde el d\u00eda 1ro. de enero de 2021. \u00bfC\u00f3mo le justifico a los\ntrabajadores sociales que ya cobr\u00e9 el cheque con fecha y hora se\u00f1alada?\n\u00bftendr\u00e1n que esperar a realizar el estado de cuenta que les corresponde a cada\nfin de mes para enterarse, y por ende, yo me quede sin documentaci\u00f3n legal de\nla transacci\u00f3n monetaria que la Asistencia Social, revolucionaria, me permiti\u00f3\nrecibir por mis problemas de salud?\n\nJuan Carlos Consuegra Consuegra,\n\nCarretera Central Oeste,  \nNo. 77 A, e/ Honda y 2da.,  \nCamag\u00fcey.\n\n", "link": "https://www.granma.cu/cartas/2021-01-23/exige-su-comprobante-de-pago", "original_letter_link": null, "is_response": false, "date": "2021-01-23", "comments": ["Pues esto hay que revisarlo pues parece que es una orden de BANDEC, pues aqu\u00ed en guant\u00e1namo tampoco se est\u00e1 dando comprobante al menos que no sea un deposito que usted realice, inmaginese extraer millones de pesos y no te dan ningun comprobante debes de mirar el desglose en la pantalla de la computadora del cajero"]}