{"title": "Agradecimiento a Balolo", "body": "\n\nMe dirijo a ustedes por este medio, como una lectora m\u00e1s de sus publicaciones\ny me sentir\u00eda muy agradecida si publicaran esta carta como agradecimiento al\nDr. Salvador Oliva, especialista en Angeolog\u00eda en el municipio de Jiguan\u00ed por\nsu meritoria labor y empe\u00f1o en el policl\u00ednico y hospital del municipio de\nJiguan\u00ed.\n\nPor su actitud elabor\u00e9 una carta que le hicimos llegar a la directora del\nhospital M\u00e1tires de Jiguan\u00ed para que reconociera su labor.\n\nAl cabo de 12 d\u00edas de un accidente provocado con la escalera de un carret\u00f3n mi\npap\u00e1 se hizo una herida que no parec\u00eda ser tan complicada y casi pierde la\npierna, ya que ning\u00fan m\u00e9dico que lo reconoci\u00f3 antes le detect\u00f3 que lo que\nten\u00eda eran varias venas cortadas y una arteria. Por medios propios nos\ndirigimos a la consulta del Dr. Salvador Oliva (Balolo) como todos est\u00e1n\nacostumbrados a decirle.\n\nEste m\u00e9dico se reincorpor\u00f3 a trabajar para brindar su servicio, pues ya est\u00e1\nretirado y a pesar de su juventud acumulada siente necesidad de seguir\nsalvando vidas como a mi pap\u00e1.  \n  \n\n", "link": "https://www.granma.cu/cartas/2014-04-11/agradecimiento-a-balolo", "original_letter_link": null, "is_response": false, "date": "2014-04-11", "comments": ["Reconocimientos como este estimulan tan noble y bell labor  , me uno a su criterio ,tambi\u00e9n soy jiguanicero orgulloso de contar con balolo", "lo conosco es buen profecional"]}