{"title": "Es hora de poner frenos y usar los l\u00edmites", "body": "\n\nEn esta ocasi\u00f3n estoy motivado a reflexionar un poco con ustedes y los\nlectores del espacio sobre la necesidad de usar los l\u00edmites.\n\nHe estado leyendo algunas opiniones relacionadas con las indisciplinas\nsociales y con las irregularidades en algunas \u00e1reas del trabajo por cuenta\npropia y a mi entender, todas est\u00e1n relacionadas con la poca exigencia para\nque se cumpla lo establecido y la falta de visi\u00f3n al poner en pr\u00e1ctica y dar\nlicencias a algunas de las formas del trabajo no estatal sin tener las\ncondiciones m\u00ednimas para que estas se desarrollaran sin que afectaran tanto a\nla poblaci\u00f3n, sobre todo la relacionada con los precios altos y el\ndesabastecimiento en las tiendas destinadas para brindar servicios a la\npoblaci\u00f3n .\n\nEs importante que se tengan en cuenta todas las opiniones y juntos buscar\nsoluciones a tantos problemas que hoy nos afectan, pero que s\u00ed estoy seguro de\nque tienen soluciones, solo hay que exigir que cada cual cumpla con lo que le\ntoca y no pasar la bola de mano en mano; todos sabemos qu\u00e9 nos toca, ahora\nfalta que se haga cumplir, si no nos vamos a pasar todo el tiempo diciendo y\ncompartiendo los problemas y no acabamos de dar soluciones concretas.\n\nYa sali\u00f3 la Gaceta Oficial relacionada con los trabajadores por cuenta propia\ny donde queda claro qu\u00e9 puede hacer cada cual que pidi\u00f3 licencia y casi todo\nsigue igual, es como que se perdi\u00f3 el respeto a la ley y no aparece nadie que\nla haga cumplir, \u00bfa qui\u00e9n le toca eso?\n\nSimplemente pienso que es hora de poner los frenos y usar los l\u00edmites, porque\nsi bueno es saber todo lo que est\u00e1 pasando y juntos vamos buscando o\nproponiendo soluciones pr\u00e1cticas para resolver nuestros problemas, pienso\ntambi\u00e9n que es muy peligroso ver que no se resuelven o que se ve lentitud para\nactuar sobre los males que hoy nos afectan a todos.\n\n", "link": "https://www.granma.cu/cartas/2014-01-10/es-hora-de-poner-frenos-y-usar-los-limites", "original_letter_link": null, "is_response": false, "date": "2014-01-10", "comments": []}