{"title": "Honor a quien honor merece", "body": "\n\nCuando decidimos escribir a los \u00f3rganos de prensa, lo hacemos para quejarnos,\nse\u00f1alar lo mal hecho y criticar las acciones de funcionarios e instituciones.\n\nPero no solo ocurren cosas mal hechas, que empa\u00f1an el trabajo y el amor de los\nque d\u00eda a d\u00eda nos prestan un buen servicio, nos brindan ayuda sin el inter\u00e9s\ndel dios dinero. Hay hombres y mujeres que desbordan amor, desinter\u00e9s y\naltruismo.\n\nQuisiera referirme a uno de esos seres, al cual no conozco personalmente pero\nsus acciones y comportamiento con mi hermana han suscitado una gran admiraci\u00f3n\npor \u00e9l y el colectivo que con \u00e9l trabaja.\n\nMi hermana fue remitida al hospital Hermanos Ameijeiras por una trombosis en\nambas piernas, as\u00ed se convirti\u00f3 en paciente del doctor V\u00edctor Roca Campa\u00f1a;\nEspecialista en Medicina Interna del piso 11 sala B.\n\nDesde el inicio se mostr\u00f3 interesado, dando seguimiento a la enfermedad y\nevoluci\u00f3n de mi hermana, le ayud\u00f3 a conocer su enfermedad, le transmiti\u00f3\nconfianza, autodominio que le ha ayudado no a vencer la enfermedad, pero si a\nsoportarla y enfrentarla, le ense\u00f1\u00f3 a interpretar los an\u00e1lisis que deb\u00eda\nhacerse para estar alerta.\n\nEn un gesto de desinter\u00e9s total, le dio el tel\u00e9fono de su casa, le pidi\u00f3 que\ncuando estuviera de alta y se sintiera los s\u00edntomas que indicaran un estado\ncr\u00edtico lo llamara a la hora que fuera y as\u00ed ha ocurrido en varias ocasiones.\nEn una de esas ocasiones una de esas llamadas le salv\u00f3 la vida a mi hermana.\n\nMi hermana no tiene ning\u00fan recurso material que brindarle a ese m\u00e9dico que por\ndescontado sabemos guarda con afecto las palabras de agradecimiento de sus\npacientes.\n\nHonor a quien honor merece, que se multipliquen las personas como el doctor\nRoca.\n\nFavor hacer llegar esta carta a la direcci\u00f3n del hospital Hermanos Ameijeiras.\n\n", "link": "https://www.granma.cu/cartas/2014-02-07/honor-a-quien-honor-merece", "original_letter_link": null, "is_response": false, "date": "2014-02-07", "comments": []}