{"title": "Reconocimiento al servicio de Hemodi\u00e1lisis del hospital Freire de Andrade", "body": "\n\nQuienes escriben esta carta son Rub\u00e9n Mart\u00ednez y Orbel Ortiz, pa\u00adcientes del\ncentro de di\u00e1lisis del mencionado hospital. Queremos resaltar la abnegada\nlabor de los enfermeros (as) de este lugar, as\u00ed como a los t\u00e9cnicos de re\u00faso,\nsecretaria, asistente a pacientes, encargada de sal\u00f3n y a su jefa de\nenfermeras, la se\u00f1o Mercedes Hern\u00e1ndez, quien vela junto con la doctora Al\u00adba\nque los pacientes tengan su tratamiento e insumos.\n\nAgradecemos los esfuerzos realizados por la direcci\u00f3n del hospital cuando\nmeses atr\u00e1s tuvimos serios problemas el\u00e9ctricos y gracias a la sabidur\u00eda y\nplanificaci\u00f3n del doctor Alberto Cruz, director de la instituci\u00f3n, la doctora\nMartha Medina, vicedirectora de asistencia m\u00e9dica y la licenciada Isabel Mor\u00e9,\nvicedirectora de enfermer\u00eda, no se interrumpi\u00f3 las di\u00e1lisis a los pacientes,\nni tuvimos que ir a otro centro para recibir nuestro tratamiento; re\u00adsaltamos\nque estos compa\u00f1eros est\u00e1n empe\u00f1ados insistentemente en me\u00adjorar las\ncondiciones estructurales y sanitarias del lugar.\n\nSabemos que nuestra enfermedad, la insuficiencia renal cr\u00f3nica, es una\npatolog\u00eda sumamente costosa al pa\u00eds y que el Go\u00adbierno revolucionario destina\ncuantiosos recursos pa\u00adra me\u00adjorar la calidad de vida de los pacientes. Sin\nembargo si no existieran compa\u00f1eros como los que mencionamos, que bajo su\nguardia y custodia est\u00e1n no solo los recursos y bienes de la Revoluci\u00f3n, sino\nque est\u00e1 la vida de muchos pacientes que dependen de un ri\u00f1\u00f3n artificial para\nvivir y ha\u00adcen que nosotros no solo mejoremos nuestra calidad de vida y que\nformemos una familia, pues pasamos mucho tiempo en el hospital, nada ser\u00eda\nposible.\n\nHoy estamos gratificando a todo el personal de esta instituci\u00f3n que labora en\nel centro de hemodi\u00e1lisis, que tiene que lidiar con nuestras alegr\u00edas y\ntristezas, con nuestras preocupaciones, y quienes nos dan tres veces por\nsemana amor, cari\u00f1o y vida.  \n  \nRub\u00e9n Mart\u00ednez,  \nCalle 5ta, No. 75, Habana Nueva,  \nGuanabacoa,  \nLa Habana,  \nOrbel Ortiz Edificio 22, apto. 9,  \nMicro San Jos\u00e9 de las Lajas,  \nMayabeque\n\n", "link": "https://www.granma.cu/cartas/2015-05-07/reconocimiento-al-servicio-de-hemodialisis-del-hospital-freire-de-andrade", "original_letter_link": null, "is_response": false, "date": "2015-05-07", "comments": ["buenas una pregunta, soy de venezuela y deseo viajar a cuba , y me dialisan, que posoibilidades y que hay de cierto que la persona que va de viaje y necesita dialisarse puede acudir a ese centro de hemodilisis, y es cierto envienme informacion gracias"]}