{"title": "Framboyanes amenazan  con caerse en pleno Vedado", "body": "\n\nDesde hace varios a\u00f1os venimos planteando en las asambleas de rendici\u00f3n de\ncuentas de nuestra circunscripci\u00f3n y en otras instancias del municipio de\nPlaza de la Revoluci\u00f3n, la situaci\u00f3n de peligro que tenemos los vecinos\nresidentes en el edificio n\u00famero 1068, de la calle 21, entre 12 y 14, Vedado,\ncon dos framboyanes de altura considerable situados frente al inmueble, que se\nencuentran en mal estado y presentan alto riesgo de caerse en cualquier\nmomento.\n\nEn los \u00faltimos tiempos ya es algo habitual el desprendimiento de ramas de\napreciable tama\u00f1o, situaci\u00f3n que en m\u00e1s de una ocasi\u00f3n ha estado a punto de\ncausar lesiones a quienes pasan por debajo de ambos \u00e1rboles, adem\u00e1s de afectar\nlos cables del tendido el\u00e9ctrico y telef\u00f3nico, perjudicando en no pocas\nocasiones el poder recibir tan vitales servicios.\n\nPara colmo las ra\u00edces no solo han levantado parte de la acera, sino que\ntambi\u00e9n recientemente da\u00f1aron dos tuber\u00edas de agua del edificio, provocando\nsalideros y alteraciones en el suministro de tan vital l\u00edquido.\n\nLo otro es que en los dos \u00e1rboles se concentran en horas de la noche numerosos\nmurci\u00e9lagos, que obligan a los vecinos a cerrar herm\u00e9ticamente los balcones.\n\n\u00bfSer\u00e1 posible talarlos antes de que causen lamentables accidentes, da\u00f1en la\ncisterna o provoquen otros perjuicios?\n\nOmar P\u00e9rez Hern\u00e1ndez  \nEdificio 1068, apartamento 3, entre 12 y 14, municipio de Plaza de la\nRevoluci\u00f3n, La Habana\n\n", "link": "https://www.granma.cu/cartas/2017-06-16/framboyanes-amenazan-con-caerse-en-pleno-vedado", "original_letter_link": null, "is_response": false, "date": "2017-06-16", "comments": ["Detr\u00e1s de mi edificio siempre han existido dos \u00e1rboles de framboy\u00e1n y nunca he visto un murci\u00e9lago."]}