{"title": "No est\u00e1 conforme  con la nueva chequera  que recibe", "body": "\n\n(\u2026) Mi nombre es Xiomara S\u00e1nchez y mi esposo falleci\u00f3 el 3 de julio del 2017.\nEn lo que saqu\u00e9 la certificaci\u00f3n de defunci\u00f3n y la de matrimonio, present\u00e9 los\ndocumentos el 3 de agosto y mi chequera venci\u00f3 en agosto, es decir, que por\nsuerte no cobr\u00e9 septiembre por ese motivo. El caso es que yo me acog\u00ed a la\nchequera de mi esposo, Mario P\u00e9rez Guerra, que cobraba 305,00 pesos, y la m\u00eda\nera de 242,00. En octubre me llegan unos cheques e incluso del mes de\nseptiembre me llegan 135,00 pesos, o sea, que ven\u00eda como si yo hubiera cobrado\nese mes. Expliqu\u00e9 que yo hab\u00eda entregado mi chequera vac\u00eda en el mes de agosto\ny dijeron que en enero me pagar\u00edan los 242,00 pesos. Conclusi\u00f3n, que la\ntarjeta me lleg\u00f3 con 377,00 pesos. Yo trabaj\u00e9 25 a\u00f1os en la textilera 9 de\nabril y me aumentaron solo 72,00 pesos; no me parece justo.\n\nXiomara S\u00e1nchez,  \n26 a No. 9702 entre 97 y 99, Las brisas, Cotorro,  \nLa Habana.\n\n", "link": "https://www.granma.cu/cartas/2018-11-09/no-esta-conforme-con-la-nueva-chequera-que-recibe", "original_letter_link": null, "is_response": false, "date": "2018-11-09", "comments": ["ya que estan hablando de las chequeras, este problema es en Holguin municipio cabesera donde le entregan las chequeras o cualquier otro tramite que debe de haser un ansiano que no hay condisiones creadas para que los ansianos se sienten o espacio eso es criminal ver como la cola dobla la esquina al menos mis padres no pueden ya estan llegadon a los 80 hay un local en carretera de gibara al lado de una oficina de la onat donde pudieran habilitar como si son bancos de cemento pero hay espacio y sombra, hablamos mucho de que nuestra poblacion esta envejeciendo pero no miramos estos detalles, yo que tengo 51 a\u00f1os no puedo estar de pie mucho tiempo pues esos ancianos que pasan de los 70 por favor hagan algo"]}