{"title": "A los que solo ven manchas", "body": "\n\nSi us\u00e1ramos nuestra inteligencia para hacer el bien y desterr\u00e1ramos el\nego\u00edsmo, el mundo ser\u00eda mucho mejor. A veces escuchamos opiniones que nos\ndejan estupefactos, incluso de personas con nivel universitario, t\u00edtulo que\nobtuvieron gracias a la Revoluci\u00f3n. Ejemplos hay muchos.  \nHe escuchado a quien dice que \u00abdebieron cerrar la frontera antes, que debido a\neso los turistas introdujeron el coronavirus\u00bb. Si los turistas no lo hubiesen\nhecho, lo hubieran hecho, los cubanos que se encontraban en el extranjero\u2026\nEstos son momentos de ayudar, de dar ideas que son bienvenidas, dejemos la\ncr\u00edtica insidiosa... Agradezcamos todo el esfuerzo que hace el pa\u00eds en aras de\nprotegernos. Ser\u00eda interesante que publicaran, am\u00e9n de que lo critiquen,\ncu\u00e1nto cuesta al Estado mantener en aislamiento cada persona, y cu\u00e1nto se deja\nde producir por las que est\u00e1n en sus casas ganando, al menos el primer mes, el\n100 % de su salario. Sabemos que no es una sociedad perfecta, pero lo m\u00ednimo\nque debemos hacer es reconocer lo positivo.\n\nRoberto Alvarez Os\u00e9s,\n\nVilla Clara.\n\n", "link": "https://www.granma.cu/cartas/2020-04-04/a-los-que-solo-ven-manchas", "original_letter_link": null, "is_response": false, "date": "2020-04-04", "comments": []}