{"title": "Caen los troncos secos, pero el problema sigue sin due\u00f1o", "body": "\n\nEl pasado 4 de marzo entregu\u00e9 a la Direcci\u00f3n Provincial de Servicios Comunales\nde La Habana una carta donde dec\u00eda que un enorme tronco de un \u00e1rbol,\ncompletamente seco, hab\u00eda ca\u00eddo sobre la entrada de dos casas. Por suerte esto\nocurri\u00f3 en horas de la madrugada, sin da\u00f1os a personas.\n\nEl \u00e1rbol est\u00e1 situado en la acera de la calle F, entre 25 y 27, en el Vedado,\nfrente a la casa con el n\u00famero 604. Esta es una acera muy transitada que da\nacceso a los hospitales Oncol\u00f3gico, Fructuoso Rodr\u00edguez y Pedi\u00e1trico Borr\u00e1s\nAstorga.\n\nDe Comunales me enviaron a la Empresa Aurora, donde de manera absurda me\ndijeron que yo deb\u00eda ir al Ministerio de Agricultura para solicitar la poda\ndel \u00e1rbol.\n\nCon el paso de la perturbaci\u00f3n cicl\u00f3nica reciente, cay\u00f3 otro enorme tronco\nsobre la calle. \u00bfC\u00f3mo resolver este peligro?\n\nIng. Alberto Mar\u00edn R.,\n\nCalle F, No. 606, e/ 25 y 27, Vedado, Plaza de la Revoluci\u00f3n,\n\nLa Habana.\n\n", "link": "https://www.granma.cu/cartas/2020-10-02/caen-los-troncos-secos-pero-el-problema-sigue-sin-dueno", "original_letter_link": null, "is_response": false, "date": "2020-10-02", "comments": ["Hoy s\u00e1bado vino una brigada especiaizada y elimin\u00f3 las ramas peligrosas. Solo queda pendiente eliminar el a\u00fan peligroso  tronco, para lo cual enviar\u00e1n a otra brigada con otro equipamiento.  Muy agrdecido."]}