{"title": "\u00bfLa misma bola de helado vale el doble?", "body": "\n\nLos usuarios consideramos un abuso y una falta de respeto lo ocurrido en la\nhelader\u00eda Guam\u00e1, en Holgu\u00edn. Hasta el jueves, 19 de agosto, la bola de helado\ncostaba dos pesos. Al d\u00eda siguiente, en la ma\u00f1ana, la misma bola, despachada\npor los mismos empleados, val\u00eda el doble, cuatro pesos, as\u00ed, sin explicaci\u00f3n\nalguna. Si quieres, la llevas; si no, d\u00e9jala.\n\nConsidero que el pueblo merece al menos una explicaci\u00f3n convincente por ese\naumento repentino.\n\nEric Leal \u00c1lvarez, calle Cuba,\n\nNo. 339, esquina a Uni\u00f3n, Holgu\u00edn.\n\n", "link": "https://www.granma.cu/cartas/2021-09-03/la-misma-bola-de-helado-vale-el-doble", "original_letter_link": null, "is_response": false, "date": "2021-09-03", "comments": []}